publicaddr/__init__.py
publicaddr/constants.py
publicaddr/handlers.py
publicaddr/publicaddr.yml
publicaddr/randprov.py
publicaddr-0.17.0.dist-info/licenses/LICENSE
tests/__init__.py
tests/test_akamai.py
tests/test_cloudflare.py
tests/test_framasoft.py
tests/test_google.py
tests/test_icanhazip.py
tests/test_ifconfigme.py
tests/test_ipify.py
tests/test_lookup.py
tests/test_matrix.py
tests/test_opendns.py
publicaddr-0.17.0.dist-info/METADATA
publicaddr-0.17.0.dist-info/WHEEL
publicaddr-0.17.0.dist-info/top_level.txt
publicaddr-0.17.0.dist-info/RECORD
