Metadata-Version: 2.4
Name: publicaddr
Version: 0.17.0
Summary: Getting your public IP v4 and v6
Home-page: https://github.com/dmachard/python-publicaddr
Author: Denis MACHARD
Author-email: d.machard@gmail.com
Keywords: public ip dns http google akamai opendns cloudflare
Platform: any
Classifier: License :: OSI Approved :: MIT License
Classifier: Programming Language :: Python :: 3
Classifier: Operating System :: OS Independent
Classifier: Topic :: Software Development :: Libraries
License-File: LICENSE
Requires-Dist: requests
Requires-Dist: dnspython
Requires-Dist: pyyaml
Requires-Dist: aiostun
Requires-Dist: checkifvalid
Dynamic: author
Dynamic: author-email
Dynamic: classifier
Dynamic: description
Dynamic: description-content-type
Dynamic: home-page
Dynamic: keywords
Dynamic: license-file
Dynamic: platform
Dynamic: requires-dist
Dynamic: summary
